dtx_attacks/__init__.py
dtx_attacks/attacks/__init__.py
dtx_attacks/attacks/attackers/__init__.py
dtx_attacks/attacks/attackers/actor/__init__.py
dtx_attacks/attacks/attackers/actor/runner.py
dtx_attacks/attacks/attackers/autodan/__init__.py
dtx_attacks/attacks/attackers/autodan/prefix_prompt_manager.py
dtx_attacks/attacks/attackers/autodan/runner.py
dtx_attacks/attacks/attackers/autodan/targetloss_selection.py
dtx_attacks/attacks/attackers/base/__init__.py
dtx_attacks/attacks/attackers/base/results.py
dtx_attacks/attacks/attackers/base/utils.py
dtx_attacks/attacks/attackers/bon/__init__.py
dtx_attacks/attacks/attackers/bon/runner.py
dtx_attacks/attacks/attackers/bon/utils.py
dtx_attacks/attacks/attackers/crescendo/__init__.py
dtx_attacks/attacks/attackers/crescendo/prompts.py
dtx_attacks/attacks/attackers/crescendo/runner.py
dtx_attacks/attacks/attackers/deep_inception/__init__.py
dtx_attacks/attacks/attackers/deep_inception/mutation.py
dtx_attacks/attacks/attackers/deep_inception/runner.py
dtx_attacks/attacks/attackers/gptfuzzer/__init__.py
dtx_attacks/attacks/attackers/gptfuzzer/classification_scorer.py
dtx_attacks/attacks/attackers/gptfuzzer/crossover.py
dtx_attacks/attacks/attackers/pair/__init__.py
dtx_attacks/attacks/attackers/pair/historical_insight.py
dtx_attacks/attacks/attackers/pair/runner.py
dtx_attacks/attacks/attackers/tap/__init__.py
dtx_attacks/attacks/attackers/tap/base.py
dtx_attacks/attacks/attackers/tap/delete_off_topic.py
dtx_attacks/attacks/attackers/tap/introspection.py
dtx_attacks/attacks/attackers/tap/runner.py
dtx_attacks/attacks/attackers/tap/scores_selection.py
dtx_attacks/attacks/attackers/telemetry/__init__.py
dtx_attacks/attacks/attackers/telemetry/progress_hook.py
dtx_attacks/attacks/datasets/__init__.py
dtx_attacks/attacks/datasets/attack_dataset.py
dtx_attacks/attacks/datasets/example.py
dtx_attacks/attacks/mutation/__init__.py
dtx_attacks/attacks/mutation/art/__init__.py
dtx_attacks/attacks/mutation/art/handler.py
dtx_attacks-0.4.0.dist-info/METADATA
dtx_attacks-0.4.0.dist-info/WHEEL
dtx_attacks-0.4.0.dist-info/RECORD
