Metadata-Version: 2.3
Name: dtx-attacks
Version: 0.4.0
Summary: 
Author: JC
Author-email: jitendra@detoxio.ai
Requires-Python: >=3.11,<3.14
Classifier: Programming Language :: Python :: 3
Classifier: Programming Language :: Python :: 3.11
Classifier: Programming Language :: Python :: 3.12
Classifier: Programming Language :: Python :: 3.13
Provides-Extra: torch
Requires-Dist: art (>=6.5,<7.0)
Requires-Dist: fastchat (>=0.1.0,<0.2.0)
Requires-Dist: jsonlines (>=4.0.0,<5.0.0)
Requires-Dist: litellm (>=1.63.6,<2.0.0)
Requires-Dist: loguru (>=0.7.3,<0.8.0)
Requires-Dist: nltk (>=3.9.1,<4.0.0)
Requires-Dist: openai (>=1.99.0,<2.0.0)
Requires-Dist: pandas (>=2.3.2,<3.0.0)
Requires-Dist: python-dotenv (>=1.0.0,<2.0.0)
Requires-Dist: rich (>=13.7.1,<14.0.0)
Requires-Dist: torch (>=2.6.0,<2.8.0) ; extra == "torch"
Requires-Dist: transformers (>=4.55.4,<5.0.0) ; extra == "torch"
